{
  "placeholderImages": [
    {
      "id": "hero-background",
      "description": "A beautiful overhead shot of a table laden with various gourmet dishes and pastries.",
      "imageUrl": "https://images.unsplash.com/photo-1545216560-68430ad77342?crop=entropy&cs=tinysrgb&fit=max&fm=jpg&ixid=M3w3NDE5ODJ8MHwxfHNlYXJjaHwxfHxmb29kJTIwc3ByZWFkfGVufDB8fHx8MTc1OTQ3OTUzNHww&ixlib=rb-4.1.0&q=80&w=1080",
      "imageHint": "food spread",
      "width": 1920,
      "height": 1080
    },
    {
      "id": "about-portrait",
      "description": "A professional and friendly portrait of Paula Rebollar.",
      "imageUrl": "/img/other/paula_lecordonblue1.webp",
      "imageHint": "chef portrait",
      "width": 800,
      "height": 1000
    },
    {
      "id": "gallery-pastry-1",
      "description": "Strawberry & coconut tart",
      "imageUrl": "/img/pastry/pastry1.webp",
      "imageHint": "pâtisserie",
      "width": 800,
      "height": 1000
    },
    {
      "id": "gallery-pastry-2",
      "description": "Opera cake",
      "imageUrl": "/img/pastry/pastry2.webp",
      "imageHint": "pâtisserie",
      "width": 800,
      "height": 1000
    },
    {
      "id": "gallery-pastry-3",
      "description": "Red berry, hibiscus & mascarpone mousse cake",
      "imageUrl": "/img/pastry/pastry3.webp",
      "imageHint": "pâtisserie",
      "width": 800,
      "height": 1000
    },
    {
      "id": "gallery-pastry-4",
      "description": "Caramel & coffee entremet",
      "imageUrl": "/img/pastry/pastry4.webp",
      "imageHint": "pâtisserie",
      "width": 800,
      "height": 1000
    },
    {
      "id": "gallery-pastry-5",
      "description": "Apple, cardamom & pecan nut petite-gateaux",
      "imageUrl": "/img/pastry/pastry5.webp",
      "imageHint": "pâtisserie",
      "width": 800,
      "height": 1000
    },
    {
      "id": "gallery-pastry-6",
      "description": "Mango, raspberry & cashew nut fashion dessert",
      "imageUrl": "/img/pastry/pastry6.webp",
      "imageHint": "pâtisserie",
      "width": 800,
      "height": 1000
    },
    {
      "id": "gallery-pastry-7",
      "description": "Chocolate hazelnut intense dessert",
      "imageUrl": "/img/pastry/pastry7.webp",
      "imageHint": "pâtisserie",
      "width": 800,
      "height": 1000
    },
    {
      "id": "gallery-pastry-8",
      "description": "Lime and berry domes",
      "imageUrl": "/img/pastry/pastry8.webp",
      "imageHint": "pâtisserie",
      "width": 800,
      "height": 1000
    },
    {
      "id": "gallery-pastry-9",
      "description": "Chocolate equinox dessert, gluten free",
      "imageUrl": "/img/pastry/pastry9.webp",
      "imageHint": "pâtisserie",
      "width": 800,
      "height": 1000
    },
    {
      "id": "gallery-pastry-10",
      "description": "Spiced clementine, citrus genoise sponge, almond crémeux & intense chocolate cream",
      "imageUrl": "/img/pastry/pastry10.webp",
      "imageHint": "pâtisserie",
      "width": 800,
      "height": 1000
    },
    {
      "id": "gallery-pastry-11",
      "description": "Festive chocolate sculpture",
      "imageUrl": "/img/pastry/pastry11.webp",
      "imageHint": "pâtisserie",
      "width": 800,
      "height": 1000
    },
    {
      "id": "gallery-pastry-12",
      "description": "Pulled sugar sculpture",
      "imageUrl": "/img/pastry/pastry12.webp",
      "imageHint": "pâtisserie",
      "width": 800,
      "height": 1000
    },
    {
      "id": "gallery-cuisine-1",
      "description": "Rabbit fricassée with mustard / sunchoke / roasted pearl onion",
      "imageUrl": "/img/cuisine/cuisine1.webp",
      "imageHint": "cuisine",
      "width": 800,
      "height": 1000
    },
    {
      "id": "gallery-cuisine-2",
      "description": "Milk-fed lamb shoulder / spiced granola / eggplant",
      "imageUrl": "/img/cuisine/cuisine2.webp",
      "imageHint": "cuisine",
      "width": 800,
      "height": 1000
    },
    {
      "id": "gallery-cuisine-3",
      "description": "Truffle chicken breast / chanterelles / buckwheat",
      "imageUrl": "/img/cuisine/cuisine3.webp",
      "imageHint": "cuisine",
      "width": 800,
      "height": 1000
    },
    {
      "id": "gallery-cuisine-4",
      "description": "Saffron risotto / mussels / razor clam / zesty foam",
      "imageUrl": "/img/cuisine/cuisine4.webp",
      "imageHint": "cuisine",
      "width": 800,
      "height": 1000
    },
    {
      "id": "gallery-cuisine-5",
      "description": "Squid ink rice puff / tuna tartar / avocado purée\n&\nPrawn tartar tartlets / salmon roe / confit lemon",
      "imageUrl": "/img/cuisine/cuisine5.webp",
      "imageHint": "cuisine",
      "width": 800,
      "height": 1000
    },
    {
      "id": "gallery-cuisine-6",
      "description": "“Ajo Blanco” / lobster / pickled vegetables",
      "imageUrl": "/img/cuisine/cuisine6.webp",
      "imageHint": "cuisine",
      "width": 800,
      "height": 1000
    },
    {
      "id": "gallery-cuisine-7",
      "description": "Bluefin tuna cheek / glazed pak choi / demi-glace",
      "imageUrl": "/img/cuisine/cuisine7.webp",
      "imageHint": "cuisine",
      "width": 800,
      "height": 1000
    },
    {
      "id": "gallery-cuisine-8",
      "description": "Squid / cockles / squid ink sponge cake",
      "imageUrl": "/img/cuisine/cuisine8.webp",
      "imageHint": "cuisine",
      "width": 800,
      "height": 1000
    },
    {
      "id": "gallery-cuisine-9",
      "description": "Tuna tartar / mustard ice cream / pickled egg yolk / tuile",
      "imageUrl": "/img/cuisine/cuisine9.webp",
      "imageHint": "cuisine",
      "width": 800,
      "height": 1000
    },
    {
      "id": "gallery-cuisine-10",
      "description": "Confit seabass / olive crust / white tomato sauce / zucchini flower",
      "imageUrl": "/img/cuisine/cuisine10.webp",
      "imageHint": "cuisine",
      "width": 800,
      "height": 1000
    },
    {
      "id": "gallery-cuisine-11",
      "description": "Trout with nori seaweed / curry sauce / daikon radish",
      "imageUrl": "/img/cuisine/cuisine11.webp",
      "imageHint": "cuisine",
      "width": 800,
      "height": 1000
    },
    {
      "id": "gallery-cuisine-12",
      "description": "Duck magret / beetroot purée / dehydrated apple",
      "imageUrl": "/img/cuisine/cuisine12.webp",
      "imageHint": "cuisine",
      "width": 800,
      "height": 1000
    }
  ]
}